streamkit/__init__.py
streamkit/__meta__.py
streamkit/publisher.py
streamkit/subscriber.py
streamkit/assets/__init__.py
streamkit/cli/__init__.py
streamkit/cli/publish.py
streamkit/cli/subscribe.py
streamkit/cli/config/__init__.py
streamkit/cli/config/edit.py
streamkit/cli/config/get.py
streamkit/cli/config/init.py
streamkit/cli/config/set.py
streamkit/cli/config/which.py
streamkit/cli/database/__init__.py
streamkit/cli/database/check.py
streamkit/cli/database/dump.py
streamkit/cli/database/init.py
streamkit/contrib/__init__.py
streamkit/contrib/logging.py
streamkit/core/__init__.py
streamkit/core/config.py
streamkit/core/exceptions.py
streamkit/core/logging.py
streamkit/database/__init__.py
streamkit/database/access.py
streamkit/database/message.py
streamkit/database/core/__init__.py
streamkit/database/core/engine.py
streamkit/database/core/init.py
streamkit/database/core/keys.py
streamkit/database/core/orm.py
streamkit/database/core/session.py
streamkit-0.3.2.dist-info/LICENSE
streamkit-0.3.2.dist-info/METADATA
streamkit-0.3.2.dist-info/WHEEL
streamkit-0.3.2.dist-info/entry_points.txt
streamkit-0.3.2.dist-info/top_level.txt
streamkit-0.3.2.dist-info/RECORD
