Metadata-Version: 2.1
Name: streamkit
Version: 0.3.2
Summary: A simple, cross-platform SDK for pub-sub messaging in Python.
Home-page: https://github.com/glentner/streamkit
Author: Geoffrey Lentner
Author-email: glentner@purdue.edu
License: Apache License
Keywords: pub-sub message broker
Platform: UNKNOWN
Classifier: Development Status :: 4 - Beta
Classifier: Programming Language :: Python :: 3
Classifier: Programming Language :: Python :: 3.8
Classifier: Programming Language :: Python :: 3.9
Classifier: License :: OSI Approved :: Apache Software License
Provides-Extra: postgres
